jsm_transactional_ruler/__init__.py
jsm_transactional_ruler/enums.py
jsm_transactional_ruler/events.py
jsm_transactional_ruler/exceptions.py
jsm_transactional_ruler/publisher.py
jsm_transactional_ruler-3.0.0.dist-info/METADATA
jsm_transactional_ruler-3.0.0.dist-info/WHEEL
jsm_transactional_ruler-3.0.0.dist-info/RECORD
