Metadata-Version: 2.1
Name: jsm-transactional-ruler
Version: 3.0.0
Summary: Lib to post user events on transactional topics
Home-page: https://juntossomosmais.com.br
Author: Juntos Somos Mais
Author-email: labs@juntossomosmais.com.br
Maintainer: Juntos Somos Mais
Maintainer-email: labs@juntossomosmais.com.br
Requires-Python: >=3.12,<4.0
Classifier: Programming Language :: Python :: 3
Classifier: Programming Language :: Python :: 3.12
Requires-Dist: Django
Requires-Dist: django-stomp (>=4.2.0)
Requires-Dist: docopt (==0.6.2)
Project-URL: Repository, https://github.com/juntossomosmais/transactional-ruler
